df_file_interchange/__init__.py
df_file_interchange/version.py
df_file_interchange/ci/__init__.py
df_file_interchange/ci/base.py
df_file_interchange/ci/examples.py
df_file_interchange/ci/structured.py
df_file_interchange/ci/extra/__init__.py
df_file_interchange/ci/extra/base.py
df_file_interchange/ci/extra/std_extra.py
df_file_interchange/ci/unit/__init__.py
df_file_interchange/ci/unit/base.py
df_file_interchange/ci/unit/currency.py
df_file_interchange/ci/unit/population.py
df_file_interchange/file/__init__.py
df_file_interchange/file/examples.py
df_file_interchange/file/rw.py
df_file_interchange/util/__init__.py
df_file_interchange/util/common.py
df_file_interchange-0.0.16a0.dist-info/LICENSE
df_file_interchange-0.0.16a0.dist-info/WHEEL
df_file_interchange-0.0.16a0.dist-info/METADATA
df_file_interchange-0.0.16a0.dist-info/RECORD
