Metadata-Version: 2.1
Name: df_file_interchange
Version: 0.0.16a0
Summary: Ensures exact round-trip saves with Pandas (CSV/Parquet) and storage of validatable metadata
Author-email: Esmé Maxwell <osdev@allicient.co.uk>
Requires-Python: >= 3.10
Classifier: Development Status :: 3 - Alpha
Classifier: Intended Audience :: Developers
Classifier: Intended Audience :: Science/Research
Classifier: License :: OSI Approved :: BSD License
Classifier: Programming Language :: Python :: 3
Classifier: Programming Language :: Python :: 3.10
Classifier: Programming Language :: Python :: 3.11
Classifier: Programming Language :: Python :: 3.12
Classifier: Topic :: File Formats
Requires-Dist: pydantic >= 2.7, < 3
Requires-Dist: pydantic-settings
Requires-Dist: numpy >= 1.26.4, < 2
Requires-Dist: pandas >= 2.2.2, < 3
Requires-Dist: pyarrow >= 16.1.0, < 17
Requires-Dist: loguru >= 0.7.2, < 1
Requires-Dist: pyyaml >= 6.0.1, < 7
Requires-Dist: pytest >= 8.2.0 ; extra == "test"
Project-URL: Documentation, https://ntnu-indecol.github.io/df_file_interchange/
Project-URL: Home, https://github.com/EXIOBASE/df_file_interchange
Project-URL: Issues, https://github.com/EXIOBASE/df_file_interchange/issues
Provides-Extra: test
